autostore/__init__.py
autostore/autostore.py
autostore/cache.py
autostore/types.py
autostore/backends/__init__.py
autostore/backends/base.py
autostore/backends/local.py
autostore/backends/s3.py
autostore/handlers/__init__.py
autostore/handlers/base.py
autostore/handlers/core.py
autostore/handlers/data.py
autostore/handlers/ml.py
autostore/handlers/registry.py
autostore-0.1.18.dist-info/licenses/LICENSE
autostore-0.1.18.dist-info/METADATA
autostore-0.1.18.dist-info/WHEEL
autostore-0.1.18.dist-info/top_level.txt
autostore-0.1.18.dist-info/RECORD
