Metadata-Version: 2.4
Name: autostore
Version: 0.1.18
Summary: File Storage Made Simple
Author-email: Asif Rahman <asiftr@gmail.com>
License: Apache License 2.0
Keywords: file storage,file management
Classifier: Programming Language :: Python :: 3.10
Classifier: Programming Language :: Python :: 3.11
Classifier: Programming Language :: Python :: 3.12
Classifier: Operating System :: OS Independent
Classifier: Environment :: Web Environment
Classifier: Topic :: Internet :: WWW/HTTP
Requires-Python: >=3.10
License-File: LICENSE
Requires-Dist: importlib-metadata; python_version < "3.10"
Provides-Extra: s3
Requires-Dist: boto3; extra == "s3"
Requires-Dist: botocore; extra == "s3"
Provides-Extra: dev
Requires-Dist: ruff; extra == "dev"
Requires-Dist: ipykernel; extra == "dev"
Requires-Dist: pytest; extra == "dev"
Requires-Dist: nbformat; extra == "dev"
Provides-Extra: test
Requires-Dist: boto3; extra == "test"
Requires-Dist: botocore; extra == "test"
Requires-Dist: polars; extra == "test"
Requires-Dist: torch; extra == "test"
Requires-Dist: numpy; extra == "test"
Requires-Dist: scipy; extra == "test"
Dynamic: license-file
